AutoAgent/__init__.py
AutoAgent/agent_utils.py
AutoAgent/core.py
AutoAgent/core_constants.py
AutoAgent/utils.py
AutoAgent-0.0.2.dist-info/METADATA
AutoAgent-0.0.2.dist-info/WHEEL
AutoAgent-0.0.2.dist-info/top_level.txt
AutoAgent-0.0.2.dist-info/RECORD
