Metadata-Version: 2.1
Name: AutoAgent
Version: 0.0.2
Summary: Autonomous AI Agents Framework with Asynchronous Agent Loop Running Environment
Author: Xichen Derek Ding
Author-email: dingo0927@126.com
Project-URL: homepage, http://www.deepnlp.org/blog?category=agent
Project-URL: repository, https://github.com/AI-Hub-Admin/AutoAgent
Keywords: Autonomous Agents,AutoAgent,generation
Classifier: Development Status :: 3 - Alpha
Classifier: Intended Audience :: Developers
Classifier: Topic :: Software Development :: Build Tools
Classifier: License :: OSI Approved :: MIT License
Requires-Python: >=3.4
Requires-Dist: requests>=2.17.0
Requires-Dist: uuid>=1.30
